arcane/criteo/__init__.py
arcane/criteo/criteo.py
arcane/criteo/exceptions.py
arcane_criteo-1.0.6.dist-info/METADATA
arcane_criteo-1.0.6.dist-info/WHEEL
arcane_criteo-1.0.6.dist-info/RECORD
